jigglypuffRL/__init__.py
jigglypuffRL/common/__init__.py
jigglypuffRL/common/policies.py
jigglypuffRL/common/values.py
jigglypuffRL/deeprl/__init__.py
jigglypuffRL/deeprl/ppo1/__init__.py
jigglypuffRL/deeprl/ppo1/ppo1.py
jigglypuff_rl-0.0.1.dist-info/LICENSE
jigglypuff_rl-0.0.1.dist-info/METADATA
jigglypuff_rl-0.0.1.dist-info/WHEEL
jigglypuff_rl-0.0.1.dist-info/top_level.txt
jigglypuff_rl-0.0.1.dist-info/RECORD
